{"records":[{"gameKindId":"1","details":[{"brand":"AW","gameKindCode":"1-","gameKindId":1,"netWin":347.53,"ownNetWin":0,"memberCount":5,"txnCount":1425,"totalBets":4666.96,"jackpot":0,"jpContribution":0},{"brand":"BNG","gameKindCode":"1-","gameKindId":1,"netWin":442.75,"ownNetWin":0,"memberCount":4,"txnCount":431,"totalBets":1171.5,"jackpot":0,"jpContribution":0},{"brand":"BP","gameKindCode":"1-","gameKindId":1,"netWin":-2773,"ownNetWin":0,"memberCount":3,"txnCount":1401,"totalBets":5720,"jackpot":0,"jpContribution":0},{"brand":"CQ9","gameKindCode":"1-","gameKindId":1,"netWin":532.16,"ownNetWin":0,"memberCount":4,"txnCount":311,"totalBets":982.06,"jackpot":0,"jpContribution":0},{"brand":"EVOPLAY","gameKindCode":"1-","gameKindId":1,"netWin":142,"ownNetWin":0,"memberCount":2,"txnCount":360,"totalBets":1240,"jackpot":0,"jpContribution":0},{"brand":"GMT","gameKindCode":"1-","gameKindId":1,"netWin":-2500.8,"ownNetWin":0,"memberCount":3,"txnCount":1809,"totalBets":4843.62,"jackpot":0,"jpContribution":0},{"brand":"HBN","gameKindCode":"1-","gameKindId":1,"netWin":-312.65,"ownNetWin":0,"memberCount":4,"txnCount":1911,"totalBets":3452.5,"jackpot":0,"jpContribution":0},{"brand":"JDB","gameKindCode":"1-","gameKindId":1,"netWin":11437.9,"ownNetWin":0,"memberCount":26,"txnCount":19158,"totalBets":155927.5,"jackpot":0,"jpContribution":0},{"brand":"JOKER","gameKindCode":"1-","gameKindId":1,"netWin":985.3,"ownNetWin":0,"memberCount":22,"txnCount":10549,"totalBets":43930.6,"jackpot":0,"jpContribution":0},{"brand":"KISS918","gameKindCode":"1-","gameKindId":1,"netWin":27626.6,"ownNetWin":0,"memberCount":38,"txnCount":570,"totalBets":0,"jackpot":0,"jpContribution":0},{"brand":"MGP","gameKindCode":"1-","gameKindId":1,"netWin":437.8,"ownNetWin":0,"memberCount":4,"txnCount":516,"totalBets":1975,"jackpot":0,"jpContribution":0},{"brand":"PG","gameKindCode":"1-","gameKindId":1,"netWin":5008.06,"ownNetWin":0,"memberCount":31,"txnCount":29514,"totalBets":95991.3,"jackpot":0,"jpContribution":0},{"brand":"PNG","gameKindCode":"1-","gameKindId":1,"netWin":49.88,"ownNetWin":0,"memberCount":3,"txnCount":2420,"totalBets":7150,"jackpot":0,"jpContribution":0},{"brand":"PP","gameKindCode":"1-","gameKindId":1,"netWin":540.93,"ownNetWin":0,"memberCount":9,"txnCount":2866,"totalBets":11827.08,"jackpot":0,"jpContribution":0},{"brand":"PTO","gameKindCode":"1-","gameKindId":1,"netWin":758.66,"ownNetWin":0,"memberCount":7,"txnCount":470,"totalBets":3381,"jackpot":0,"jpContribution":0},{"brand":"RT","gameKindCode":"1-","gameKindId":1,"netWin":-728.7,"ownNetWin":0,"memberCount":4,"txnCount":1315,"totalBets":3476,"jackpot":0,"jpContribution":0},{"brand":"SG","gameKindCode":"1-","gameKindId":1,"netWin":415.5,"ownNetWin":0,"memberCount":4,"txnCount":671,"totalBets":2474,"jackpot":0,"jpContribution":0}],"memberCount":"173","txnCount":"75697","totalBets":"348209.12","netWin":"42409.92","ownNetWin":"0","jackpot":"0","jpContribution":"0"},{"gameKindId":"6","details":[{"brand":"AW","gameKindCode":"5-6-","gameKindId":6,"netWin":1730.3,"ownNetWin":0,"memberCount":8,"txnCount":10240,"totalBets":148512.1,"jackpot":0,"jpContribution":0},{"brand":"CQ9","gameKindCode":"5-6-","gameKindId":6,"netWin":100,"ownNetWin":0,"memberCount":1,"txnCount":1,"totalBets":398,"jackpot":0,"jpContribution":0},{"brand":"FC","gameKindCode":"5-6-","gameKindId":6,"netWin":239.3,"ownNetWin":0,"memberCount":2,"txnCount":13,"totalBets":900.6,"jackpot":0,"jpContribution":0},{"brand":"JDB","gameKindCode":"5-6-","gameKindId":6,"netWin":837.8,"ownNetWin":0,"memberCount":7,"txnCount":127,"totalBets":23084.4,"jackpot":0,"jpContribution":0},{"brand":"SG","gameKindCode":"5-6-","gameKindId":6,"netWin":-126.3,"ownNetWin":0,"memberCount":7,"txnCount":26,"totalBets":23831.7,"jackpot":0,"jpContribution":0}],"memberCount":"25","txnCount":"10407","totalBets":"196726.8","netWin":"2781.1","ownNetWin":"0","jackpot":"0","jpContribution":"0"},{"gameKindId":"7","details":[{"brand":"JDB","gameKindCode":"5-7-","gameKindId":7,"netWin":72.9,"ownNetWin":0,"memberCount":3,"txnCount":278,"totalBets":499.2,"jackpot":0,"jpContribution":0}],"memberCount":"3","txnCount":"278","totalBets":"499.2","netWin":"72.9","ownNetWin":"0","jackpot":"0","jpContribution":"0"},{"gameKindId":"8","details":[{"brand":"IGK","gameKindCode":"8-","gameKindId":8,"netWin":20,"ownNetWin":0,"memberCount":1,"txnCount":1,"totalBets":20,"jackpot":0,"jpContribution":0},{"brand":"SABA","gameKindCode":"8-","gameKindId":8,"netWin":29620,"ownNetWin":0,"memberCount":2,"txnCount":7,"totalBets":31630,"jackpot":0,"jpContribution":0},{"brand":"SBO","gameKindCode":"8-","gameKindId":8,"netWin":20553,"ownNetWin":0,"memberCount":2,"txnCount":7,"totalBets":23001,"jackpot":0,"jpContribution":0}],"memberCount":"5","txnCount":"15","totalBets":"54651","netWin":"50193","ownNetWin":"0","jackpot":"0","jpContribution":"0"},{"gameKindId":"10","details":[{"brand":"AG","gameKindCode":"4-10-","gameKindId":10,"netWin":1086,"ownNetWin":0,"memberCount":1,"txnCount":186,"totalBets":8834,"jackpot":0,"jpContribution":0},{"brand":"SA","gameKindCode":"4-10-","gameKindId":10,"netWin":-595.5,"ownNetWin":0,"memberCount":4,"txnCount":171,"totalBets":8911.5,"jackpot":0,"jpContribution":0},{"brand":"SEXY","gameKindCode":"4-10-","gameKindId":10,"netWin":-5775.2,"ownNetWin":0,"memberCount":6,"txnCount":2775,"totalBets":122579.2,"jackpot":0,"jpContribution":0}],"memberCount":"11","txnCount":"3132","totalBets":"140324.7","netWin":"-5284.7","ownNetWin":"0","jackpot":"0","jpContribution":"0"},{"gameKindId":"13","details":[{"brand":"EVO","gameKindCode":"4-13-","gameKindId":13,"netWin":150,"ownNetWin":0,"memberCount":1,"txnCount":15,"totalBets":150,"jackpot":0,"jpContribution":0},{"brand":"SA","gameKindCode":"4-13-","gameKindId":13,"netWin":990,"ownNetWin":0,"memberCount":2,"txnCount":191,"totalBets":1665,"jackpot":0,"jpContribution":0}],"memberCount":"3","txnCount":"206","totalBets":"1815","netWin":"1140","ownNetWin":"0","jackpot":"0","jpContribution":"0"},{"gameKindId":"15","details":[{"brand":"SA","gameKindCode":"4-15-","gameKindId":15,"netWin":300,"ownNetWin":0,"memberCount":1,"txnCount":10,"totalBets":700,"jackpot":0,"jpContribution":0},{"brand":"SEXY","gameKindCode":"4-15-","gameKindId":15,"netWin":100,"ownNetWin":0,"memberCount":1,"txnCount":15,"totalBets":160,"jackpot":0,"jpContribution":0}],"memberCount":"2","txnCount":"25","totalBets":"860","netWin":"400","ownNetWin":"0","jackpot":"0","jpContribution":"0"},{"gameKindId":"25","details":[{"brand":"EVO","gameKindCode":"4-25-","gameKindId":25,"netWin":325,"ownNetWin":0,"memberCount":1,"txnCount":105,"totalBets":650,"jackpot":0,"jpContribution":0}],"memberCount":"1","txnCount":"105","totalBets":"650","netWin":"325","ownNetWin":"0","jackpot":"0","jpContribution":"0"},{"gameKindId":"30","details":[{"brand":"SVL","gameKindCode":"30-","gameKindId":30,"netWin":2,"ownNetWin":2,"memberCount":1,"txnCount":1,"totalBets":2,"jackpot":0,"jpContribution":0}],"memberCount":"1","txnCount":"1","totalBets":"2","netWin":"2","ownNetWin":"2","jackpot":"0","jpContribution":"0"},{"gameKindId":"42","details":[{"brand":"EVO","gameKindCode":"4-42-","gameKindId":42,"netWin":80,"ownNetWin":0,"memberCount":1,"txnCount":5,"totalBets":80,"jackpot":0,"jpContribution":0}],"memberCount":"1","txnCount":"5","totalBets":"80","netWin":"80","ownNetWin":"0","jackpot":"0","jpContribution":"0"}],"sum":{"memberCount":"225","txnCount":"89871","totalBets":"743817.82","netWin":"92119.22","ownNetWin":"2","jackpot":"0","jpContribution":"0"}}