{"records":[{"gameKindId":"1","details":[{"brand":"AW","gameKindCode":"1-","gameKindId":1,"netWin":6661.99,"ownNetWin":0,"memberCount":2,"txnCount":7844,"totalBets":84851.2,"jackpot":0,"jpContribution":0},{"brand":"BNG","gameKindCode":"1-","gameKindId":1,"netWin":-1318.6,"ownNetWin":0,"memberCount":3,"txnCount":2850,"totalBets":8791.5,"jackpot":0,"jpContribution":0},{"brand":"BP","gameKindCode":"1-","gameKindId":1,"netWin":62,"ownNetWin":0,"memberCount":1,"txnCount":22,"totalBets":80,"jackpot":0,"jpContribution":0},{"brand":"CQ9","gameKindCode":"1-","gameKindId":1,"netWin":91.7,"ownNetWin":0,"memberCount":4,"txnCount":378,"totalBets":1216.7,"jackpot":0,"jpContribution":0},{"brand":"EVOPLAY","gameKindCode":"1-","gameKindId":1,"netWin":47,"ownNetWin":0,"memberCount":1,"txnCount":15,"totalBets":65,"jackpot":0,"jpContribution":0},{"brand":"HBN","gameKindCode":"1-","gameKindId":1,"netWin":42.15,"ownNetWin":0,"memberCount":1,"txnCount":392,"totalBets":1123.5,"jackpot":0,"jpContribution":0},{"brand":"JDB","gameKindCode":"1-","gameKindId":1,"netWin":-5200.7,"ownNetWin":0,"memberCount":20,"txnCount":15314,"totalBets":152793.2,"jackpot":0,"jpContribution":0},{"brand":"JOKER","gameKindCode":"1-","gameKindId":1,"netWin":2165.6,"ownNetWin":0,"memberCount":19,"txnCount":10424,"totalBets":52248.8,"jackpot":0,"jpContribution":0},{"brand":"KISS918","gameKindCode":"1-","gameKindId":1,"netWin":7356,"ownNetWin":0,"memberCount":39,"txnCount":557,"totalBets":0,"jackpot":0,"jpContribution":0},{"brand":"MGP","gameKindCode":"1-","gameKindId":1,"netWin":469.2,"ownNetWin":0,"memberCount":3,"txnCount":666,"totalBets":2852.5,"jackpot":0,"jpContribution":0},{"brand":"PG","gameKindCode":"1-","gameKindId":1,"netWin":-6904.56,"ownNetWin":0,"memberCount":39,"txnCount":40596,"totalBets":178979.8,"jackpot":0,"jpContribution":0},{"brand":"PNG","gameKindCode":"1-","gameKindId":1,"netWin":-359.6,"ownNetWin":0,"memberCount":2,"txnCount":443,"totalBets":1460,"jackpot":0,"jpContribution":0},{"brand":"PP","gameKindCode":"1-","gameKindId":1,"netWin":-1060,"ownNetWin":0,"memberCount":6,"txnCount":1403,"totalBets":8416,"jackpot":0,"jpContribution":0},{"brand":"PTO","gameKindCode":"1-","gameKindId":1,"netWin":568.3,"ownNetWin":0,"memberCount":3,"txnCount":47,"totalBets":633.7,"jackpot":0,"jpContribution":0},{"brand":"RT","gameKindCode":"1-","gameKindId":1,"netWin":-724,"ownNetWin":0,"memberCount":1,"txnCount":117,"totalBets":585,"jackpot":0,"jpContribution":0},{"brand":"SG","gameKindCode":"1-","gameKindId":1,"netWin":-96.6,"ownNetWin":0,"memberCount":4,"txnCount":235,"totalBets":1242,"jackpot":0,"jpContribution":0}],"memberCount":"148","txnCount":"81303","totalBets":"495338.9","netWin":"1799.88","ownNetWin":"0","jackpot":"0","jpContribution":"0"},{"gameKindId":"6","details":[{"brand":"AW","gameKindCode":"5-6-","gameKindId":6,"netWin":1870,"ownNetWin":0,"memberCount":5,"txnCount":5756,"totalBets":44693.7,"jackpot":0,"jpContribution":0},{"brand":"CQ9","gameKindCode":"5-6-","gameKindId":6,"netWin":-1167,"ownNetWin":0,"memberCount":1,"txnCount":108,"totalBets":46143,"jackpot":0,"jpContribution":0},{"brand":"FC","gameKindCode":"5-6-","gameKindId":6,"netWin":147.2,"ownNetWin":0,"memberCount":2,"txnCount":19,"totalBets":2900,"jackpot":0,"jpContribution":0},{"brand":"JDB","gameKindCode":"5-6-","gameKindId":6,"netWin":1432.6,"ownNetWin":0,"memberCount":4,"txnCount":86,"totalBets":19727.2,"jackpot":0,"jpContribution":0},{"brand":"SG","gameKindCode":"5-6-","gameKindId":6,"netWin":6686.4,"ownNetWin":0,"memberCount":6,"txnCount":35,"totalBets":176926.7,"jackpot":0,"jpContribution":0}],"memberCount":"18","txnCount":"6004","totalBets":"290390.6","netWin":"8969.2","ownNetWin":"0","jackpot":"0","jpContribution":"0"},{"gameKindId":"7","details":[{"brand":"JDB","gameKindCode":"5-7-","gameKindId":7,"netWin":239.8,"ownNetWin":0,"memberCount":1,"txnCount":243,"totalBets":2939.7,"jackpot":0,"jpContribution":0}],"memberCount":"1","txnCount":"243","totalBets":"2939.7","netWin":"239.8","ownNetWin":"0","jackpot":"0","jpContribution":"0"},{"gameKindId":"8","details":[{"brand":"IGK","gameKindCode":"8-","gameKindId":8,"netWin":10937.215,"ownNetWin":0,"memberCount":3,"txnCount":18,"totalBets":25286,"jackpot":0,"jpContribution":0},{"brand":"SABA","gameKindCode":"8-","gameKindId":8,"netWin":10400,"ownNetWin":0,"memberCount":2,"txnCount":5,"totalBets":10400,"jackpot":0,"jpContribution":0},{"brand":"SBO","gameKindCode":"8-","gameKindId":8,"netWin":18293.8,"ownNetWin":0,"memberCount":3,"txnCount":16,"totalBets":26234,"jackpot":0,"jpContribution":0}],"memberCount":"8","txnCount":"39","totalBets":"61920","netWin":"39631.015","ownNetWin":"0","jackpot":"0","jpContribution":"0"},{"gameKindId":"10","details":[{"brand":"AG","gameKindCode":"4-10-","gameKindId":10,"netWin":344,"ownNetWin":0,"memberCount":1,"txnCount":18,"totalBets":880,"jackpot":0,"jpContribution":0},{"brand":"SA","gameKindCode":"4-10-","gameKindId":10,"netWin":-277,"ownNetWin":0,"memberCount":4,"txnCount":8,"totalBets":455,"jackpot":0,"jpContribution":0},{"brand":"SEXY","gameKindCode":"4-10-","gameKindId":10,"netWin":-12619.5,"ownNetWin":0,"memberCount":4,"txnCount":72,"totalBets":21471.5,"jackpot":0,"jpContribution":0}],"memberCount":"9","txnCount":"98","totalBets":"22806.5","netWin":"-12552.5","ownNetWin":"0","jackpot":"0","jpContribution":"0"},{"gameKindId":"12","details":[{"brand":"SA","gameKindCode":"4-12-","gameKindId":12,"netWin":-20,"ownNetWin":0,"memberCount":1,"txnCount":8,"totalBets":120,"jackpot":0,"jpContribution":0}],"memberCount":"1","txnCount":"8","totalBets":"120","netWin":"-20","ownNetWin":"0","jackpot":"0","jpContribution":"0"},{"gameKindId":"13","details":[{"brand":"EVO","gameKindCode":"4-13-","gameKindId":13,"netWin":90,"ownNetWin":0,"memberCount":1,"txnCount":42,"totalBets":450,"jackpot":0,"jpContribution":0},{"brand":"SA","gameKindCode":"4-13-","gameKindId":13,"netWin":-385,"ownNetWin":0,"memberCount":1,"txnCount":277,"totalBets":1550,"jackpot":0,"jpContribution":0},{"brand":"SEXY","gameKindCode":"4-13-","gameKindId":13,"netWin":500,"ownNetWin":0,"memberCount":1,"txnCount":72,"totalBets":860,"jackpot":0,"jpContribution":0}],"memberCount":"3","txnCount":"391","totalBets":"2860","netWin":"205","ownNetWin":"0","jackpot":"0","jpContribution":"0"},{"gameKindId":"14","details":[{"brand":"EVO","gameKindCode":"4-14-","gameKindId":14,"netWin":100,"ownNetWin":0,"memberCount":1,"txnCount":1,"totalBets":100,"jackpot":0,"jpContribution":0}],"memberCount":"1","txnCount":"1","totalBets":"100","netWin":"100","ownNetWin":"0","jackpot":"0","jpContribution":"0"},{"gameKindId":"15","details":[{"brand":"AG","gameKindCode":"4-15-","gameKindId":15,"netWin":28,"ownNetWin":0,"memberCount":1,"txnCount":2,"totalBets":84,"jackpot":0,"jpContribution":0},{"brand":"SEXY","gameKindCode":"4-15-","gameKindId":15,"netWin":138,"ownNetWin":0,"memberCount":2,"txnCount":129,"totalBets":2160,"jackpot":0,"jpContribution":0}],"memberCount":"3","txnCount":"131","totalBets":"2244","netWin":"166","ownNetWin":"0","jackpot":"0","jpContribution":"0"},{"gameKindId":"42","details":[{"brand":"EVO","gameKindCode":"4-42-","gameKindId":42,"netWin":10,"ownNetWin":0,"memberCount":1,"txnCount":1,"totalBets":10,"jackpot":0,"jpContribution":0}],"memberCount":"1","txnCount":"1","totalBets":"10","netWin":"10","ownNetWin":"0","jackpot":"0","jpContribution":"0"}],"sum":{"memberCount":"193","txnCount":"88219","totalBets":"878729.7","netWin":"38548.395","ownNetWin":"0","jackpot":"0","jpContribution":"0"}}