{"records":[{"brand":"AG","details":[{"brand":"AG","gameKindCode":"4-15-","gameKindId":15,"netWin":"6038.000000","memberCount":"1","txnCount":"16","totalBets":"10538.000000","jackpot":"0.000000","jpContribution":"0.000000"}],"memberCount":"1","txnCount":"16","totalBets":"10538","netWin":"6038","jackpot":"0","jpContribution":"0"},{"brand":"AW","details":[{"brand":"AW","gameKindCode":"1-","gameKindId":1,"netWin":"1048.320000","memberCount":"9","txnCount":"4273","totalBets":"9195.220000","jackpot":"0.000000","jpContribution":"0.000000"},{"brand":"AW","gameKindCode":"5-21-","gameKindId":21,"netWin":"1581.000000","memberCount":"2","txnCount":"105","totalBets":"13187.000000","jackpot":"0.000000","jpContribution":"0.000000"},{"brand":"AW","gameKindCode":"5-6-","gameKindId":6,"netWin":"1642.800000","memberCount":"5","txnCount":"1606","totalBets":"28293.200000","jackpot":"0.000000","jpContribution":"0.000000"}],"memberCount":"16","txnCount":"5984","totalBets":"50675.42","netWin":"4272.12","jackpot":"0","jpContribution":"0"},{"brand":"BNG","details":[{"brand":"BNG","gameKindCode":"1-","gameKindId":1,"netWin":"3481.750000","memberCount":"10","txnCount":"2967","totalBets":"25490.500000","jackpot":"0.000000","jpContribution":"0.000000"}],"memberCount":"10","txnCount":"2967","totalBets":"25490.5","netWin":"3481.75","jackpot":"0","jpContribution":"0"},{"brand":"BP","details":[{"brand":"BP","gameKindCode":"1-","gameKindId":1,"netWin":"-834.500000","memberCount":"7","txnCount":"1196","totalBets":"5165.000000","jackpot":"0.000000","jpContribution":"0.000000"}],"memberCount":"7","txnCount":"1196","totalBets":"5165","netWin":"-834.5","jackpot":"0","jpContribution":"0"},{"brand":"CQ9","details":[{"brand":"CQ9","gameKindCode":"1-","gameKindId":1,"netWin":"532.700000","memberCount":"8","txnCount":"6832","totalBets":"18046.620000","jackpot":"0.000000","jpContribution":"0.000000"},{"brand":"CQ9","gameKindCode":"5-6-","gameKindId":6,"netWin":"3995.000000","memberCount":"4","txnCount":"41","totalBets":"25188.000000","jackpot":"0.000000","jpContribution":"0.000000"}],"memberCount":"12","txnCount":"6873","totalBets":"43234.62","netWin":"4527.7","jackpot":"0","jpContribution":"0"},{"brand":"EVOA","details":[{"brand":"EVOA","gameKindCode":"4-10-","gameKindId":10,"netWin":"1152.500000","memberCount":"3","txnCount":"26","totalBets":"2037.500000","jackpot":"0.000000","jpContribution":"0.000000"},{"brand":"EVOA","gameKindCode":"4-13-","gameKindId":13,"netWin":"-210.000000","memberCount":"3","txnCount":"116","totalBets":"600.000000","jackpot":"0.000000","jpContribution":"0.000000"}],"memberCount":"6","txnCount":"142","totalBets":"2637.5","netWin":"942.5","jackpot":"0","jpContribution":"0"},{"brand":"EVOPLAY","details":[{"brand":"EVOPLAY","gameKindCode":"1-","gameKindId":1,"netWin":"-689.000000","memberCount":"4","txnCount":"249","totalBets":"815.000000","jackpot":"0.000000","jpContribution":"0.000000"}],"memberCount":"4","txnCount":"249","totalBets":"815","netWin":"-689","jackpot":"0","jpContribution":"0"},{"brand":"FC","details":[{"brand":"FC","gameKindCode":"1-","gameKindId":1,"netWin":"2561.400000","memberCount":"5","txnCount":"1723","totalBets":"7564.400000","jackpot":"0.000000","jpContribution":"0.000000"},{"brand":"FC","gameKindCode":"5-34-","gameKindId":34,"netWin":"154.500000","memberCount":"1","txnCount":"247","totalBets":"553.000000","jackpot":"0.000000","jpContribution":"0.000000"},{"brand":"FC","gameKindCode":"5-6-","gameKindId":6,"netWin":"-201.000000","memberCount":"1","txnCount":"18","totalBets":"1245.000000","jackpot":"0.000000","jpContribution":"0.000000"}],"memberCount":"7","txnCount":"1988","totalBets":"9362.4","netWin":"2514.9","jackpot":"0","jpContribution":"0"},{"brand":"GMT","details":[{"brand":"GMT","gameKindCode":"1-","gameKindId":1,"netWin":"-156.450000","memberCount":"4","txnCount":"133","totalBets":"293.000000","jackpot":"0.000000","jpContribution":"0.000000"}],"memberCount":"4","txnCount":"133","totalBets":"293","netWin":"-156.45","jackpot":"0","jpContribution":"0"},{"brand":"HBN","details":[{"brand":"HBN","gameKindCode":"1-","gameKindId":1,"netWin":"-696.000000","memberCount":"11","txnCount":"3884","totalBets":"21493.450000","jackpot":"0.000000","jpContribution":"0.000000"}],"memberCount":"11","txnCount":"3884","totalBets":"21493.45","netWin":"-696","jackpot":"0","jpContribution":"0"},{"brand":"IGK","details":[{"brand":"IGK","gameKindCode":"8-","gameKindId":8,"netWin":"116.400000","memberCount":"2","txnCount":"6","totalBets":"430.000000","jackpot":"0.000000","jpContribution":"0.000000"}],"memberCount":"2","txnCount":"6","totalBets":"430","netWin":"116.4","jackpot":"0","jpContribution":"0"},{"brand":"JDB","details":[{"brand":"JDB","gameKindCode":"1-","gameKindId":1,"netWin":"11305.550000","memberCount":"52","txnCount":"25764","totalBets":"193205.950000","jackpot":"0.000000","jpContribution":"0.000000"},{"brand":"JDB","gameKindCode":"5-6-","gameKindId":6,"netWin":"1268.500000","memberCount":"14","txnCount":"358","totalBets":"78379.800000","jackpot":"0.000000","jpContribution":"0.000000"},{"brand":"JDB","gameKindCode":"5-7-","gameKindId":7,"netWin":"-69.300000","memberCount":"2","txnCount":"89","totalBets":"388.600000","jackpot":"0.000000","jpContribution":"0.000000"}],"memberCount":"68","txnCount":"26211","totalBets":"271974.35","netWin":"12504.75","jackpot":"0","jpContribution":"0"},{"brand":"JOKER","details":[{"brand":"JOKER","gameKindCode":"1-","gameKindId":1,"netWin":"19568.500000","memberCount":"55","txnCount":"25056","totalBets":"467722.300000","jackpot":"0.000000","jpContribution":"0.000000"}],"memberCount":"55","txnCount":"25056","totalBets":"467722.3","netWin":"19568.5","jackpot":"0","jpContribution":"0"},{"brand":"KISS918","details":[{"brand":"KISS918","gameKindCode":"1-","gameKindId":1,"netWin":"12364.300000","memberCount":"50","txnCount":"699","totalBets":"0.000000","jackpot":"0.000000","jpContribution":"0.000000"}],"memberCount":"50","txnCount":"699","totalBets":"0","netWin":"12364.3","jackpot":"0","jpContribution":"0"},{"brand":"MGP","details":[{"brand":"MGP","gameKindCode":"1-","gameKindId":1,"netWin":"1267.220000","memberCount":"8","txnCount":"5219","totalBets":"18675.020000","jackpot":"0.000000","jpContribution":"0.000000"}],"memberCount":"8","txnCount":"5219","totalBets":"18675.02","netWin":"1267.22","jackpot":"0","jpContribution":"0"},{"brand":"PG","details":[{"brand":"PG","gameKindCode":"1-","gameKindId":1,"netWin":"15807.550000","memberCount":"35","txnCount":"21162","totalBets":"140427.500000","jackpot":"0.000000","jpContribution":"0.000000"},{"brand":"PG","gameKindCode":"2-","gameKindId":2,"netWin":"1345.000000","memberCount":"2","txnCount":"103","totalBets":"5817.000000","jackpot":"0.000000","jpContribution":"0.000000"}],"memberCount":"37","txnCount":"21265","totalBets":"146244.5","netWin":"17152.55","jackpot":"0","jpContribution":"0"},{"brand":"PNG","details":[{"brand":"PNG","gameKindCode":"1-","gameKindId":1,"netWin":"1670.400000","memberCount":"4","txnCount":"1446","totalBets":"9062.000000","jackpot":"0.000000","jpContribution":"0.000000"}],"memberCount":"4","txnCount":"1446","totalBets":"9062","netWin":"1670.4","jackpot":"0","jpContribution":"0"},{"brand":"PP","details":[{"brand":"PP","gameKindCode":"1-","gameKindId":1,"netWin":"507.900000","memberCount":"7","txnCount":"880","totalBets":"2402.400000","jackpot":"0.000000","jpContribution":"0.000000"}],"memberCount":"7","txnCount":"880","totalBets":"2402.4","netWin":"507.9","jackpot":"0","jpContribution":"0"},{"brand":"PTO","details":[{"brand":"PTO","gameKindCode":"1-","gameKindId":1,"netWin":"576.700000","memberCount":"9","txnCount":"6417","totalBets":"2569.500000","jackpot":"0.000000","jpContribution":"0.000000"}],"memberCount":"9","txnCount":"6417","totalBets":"2569.5","netWin":"576.7","jackpot":"0","jpContribution":"0"},{"brand":"RT","details":[{"brand":"RT","gameKindCode":"1-","gameKindId":1,"netWin":"1296.000000","memberCount":"8","txnCount":"473","totalBets":"4135.000000","jackpot":"0.000000","jpContribution":"0.000000"}],"memberCount":"8","txnCount":"473","totalBets":"4135","netWin":"1296","jackpot":"0","jpContribution":"0"},{"brand":"SA","details":[{"brand":"SA","gameKindCode":"4-10-","gameKindId":10,"netWin":"321.550000","memberCount":"9","txnCount":"539","totalBets":"35386.450000","jackpot":"0.000000","jpContribution":"0.000000"},{"brand":"SA","gameKindCode":"4-12-","gameKindId":12,"netWin":"55.000000","memberCount":"2","txnCount":"9","totalBets":"75.000000","jackpot":"0.000000","jpContribution":"0.000000"},{"brand":"SA","gameKindCode":"4-15-","gameKindId":15,"netWin":"90.000000","memberCount":"1","txnCount":"35","totalBets":"175.000000","jackpot":"0.000000","jpContribution":"0.000000"}],"memberCount":"12","txnCount":"583","totalBets":"35636.45","netWin":"466.55","jackpot":"0","jpContribution":"0"},{"brand":"SABA","details":[{"brand":"SABA","gameKindCode":"8-","gameKindId":8,"netWin":"796.000000","memberCount":"1","txnCount":"4","totalBets":"900.000000","jackpot":"0.000000","jpContribution":"0.000000"}],"memberCount":"1","txnCount":"4","totalBets":"900","netWin":"796","jackpot":"0","jpContribution":"0"},{"brand":"SBO","details":[{"brand":"SBO","gameKindCode":"8-","gameKindId":8,"netWin":"-301.160000","memberCount":"1","txnCount":"6","totalBets":"537.000000","jackpot":"0.000000","jpContribution":"0.000000"}],"memberCount":"1","txnCount":"6","totalBets":"537","netWin":"-301.16","jackpot":"0","jpContribution":"0"},{"brand":"SEXY","details":[{"brand":"SEXY","gameKindCode":"4-10-","gameKindId":10,"netWin":"1609.100000","memberCount":"18","txnCount":"2003","totalBets":"63180.900000","jackpot":"0.000000","jpContribution":"0.000000"},{"brand":"SEXY","gameKindCode":"4-12-","gameKindId":12,"netWin":"8674.500000","memberCount":"3","txnCount":"488","totalBets":"65944.500000","jackpot":"0.000000","jpContribution":"0.000000"},{"brand":"SEXY","gameKindCode":"4-13-","gameKindId":13,"netWin":"79.000000","memberCount":"3","txnCount":"743","totalBets":"2088.000000","jackpot":"0.000000","jpContribution":"0.000000"}],"memberCount":"24","txnCount":"3234","totalBets":"131213.4","netWin":"10362.6","jackpot":"0","jpContribution":"0"},{"brand":"SG","details":[{"brand":"SG","gameKindCode":"1-","gameKindId":1,"netWin":"-569.100000","memberCount":"8","txnCount":"2542","totalBets":"9529.000000","jackpot":"0.000000","jpContribution":"0.000000"},{"brand":"SG","gameKindCode":"5-6-","gameKindId":6,"netWin":"1336.000000","memberCount":"7","txnCount":"68","totalBets":"28260.300000","jackpot":"0.000000","jpContribution":"0.000000"}],"memberCount":"15","txnCount":"2610","totalBets":"37789.3","netWin":"766.9","jackpot":"0","jpContribution":"0"},{"brand":"SVL","details":[{"brand":"SVL","gameKindCode":"30-","gameKindId":30,"netWin":"100.000000","memberCount":"1","txnCount":"1","totalBets":"100.000000","jackpot":"0.000000","jpContribution":"0.000000"}],"memberCount":"1","txnCount":"1","totalBets":"100","netWin":"100","jackpot":"0","jpContribution":"0"}],"sum":{"memberCount":"380","txnCount":"117542","totalBets":"1299096.11","netWin":"98616.63","jackpot":"0","jpContribution":"0"}}