{"sum":{"totalBets":"31494.25","netWin":"1367.60","jackpot":"0.00","jpContribution":"0.00","txnCount":"7755","memberCount":"12"},"records":[{"brand":"FCV2","totalBets":"1317.05","netWin":"53.95","jackpot":"0.00","jpContribution":"0.00","txnCount":"392","memberCount":"1","ownNetWin":"0.00","details":[{"gameKindCode":"5-6-","totalBets":"1317.05","netWin":"53.95","jackpot":"0.00","jpContribution":"0.00","txnCount":"392","memberCount":"1","ownNetWin":"0.00","gameKindId":6}]},{"brand":"JDBV2","totalBets":"7080.00","netWin":"2085.00","jackpot":"0.00","jpContribution":"0.00","txnCount":"1531","memberCount":"2","ownNetWin":"0.00","details":[{"gameKindCode":"1-","totalBets":"7080.00","netWin":"2085.00","jackpot":"0.00","jpContribution":"0.00","txnCount":"1531","memberCount":"2","ownNetWin":"0.00","gameKindId":1}]},{"brand":"JILIV2","totalBets":"1595.20","netWin":"699.70","jackpot":"0.00","jpContribution":"0.00","txnCount":"605","memberCount":"3","ownNetWin":"0.00","details":[{"gameKindCode":"1-","totalBets":"1595.20","netWin":"699.70","jackpot":"0.00","jpContribution":"0.00","txnCount":"605","memberCount":"3","ownNetWin":"0.00","gameKindId":1}]},{"brand":"PGV2","totalBets":"21502.00","netWin":"-1471.05","jackpot":"0.00","jpContribution":"0.00","txnCount":"5227","memberCount":"6","ownNetWin":"0.00","details":[{"gameKindCode":"1-","totalBets":"21502.00","netWin":"-1471.05","jackpot":"0.00","jpContribution":"0.00","txnCount":"5227","memberCount":"6","ownNetWin":"0.00","gameKindId":1}]}]}