{"summary":[{"registerCount":7,"depositCount":27,"totalDeposit":"13935","totalWithdraw":"5900","totalWithdrawFee":"0","totalBetAmount":"130078.45","totalNetWin":"10467.026","totalRevenue":"8035.00","jackpot":"0.00","jpContribution":"0.00","totalPromotionAmount":"315.72","date_mmdd":"02-01","totalDeposit_p":"13,935.00","totalWithdraw_p":"5,900.00","totalBetAmount_p":"130,078.45","totalNetWin_p":"10,467.03","totalRevenue_p":"8,035.00","totalPromotionAmount_p":"315.72"},{"registerCount":11,"depositCount":52,"totalDeposit":"16937.52","totalWithdraw":"7325","totalWithdrawFee":"0","totalBetAmount":"138068.05","totalNetWin":"-2116.901","totalRevenue":"9612.52","jackpot":"0.00","jpContribution":"0.00","totalPromotionAmount":"2.75","date_mmdd":"02-02","totalDeposit_p":"16,937.52","totalWithdraw_p":"7,325.00","totalBetAmount_p":"138,068.05","totalNetWin_p":"-2,116.90","totalRevenue_p":"9,612.52","totalPromotionAmount_p":"2.75"},{"registerCount":5,"depositCount":53,"totalDeposit":"22577.58","totalWithdraw":"13300","totalWithdrawFee":"0","totalBetAmount":"201057.7","totalNetWin":"15834.87","totalRevenue":"9277.58","jackpot":"0.00","jpContribution":"0.00","totalPromotionAmount":"57.36","date_mmdd":"02-03","totalDeposit_p":"22,577.58","totalWithdraw_p":"13,300.00","totalBetAmount_p":"201,057.70","totalNetWin_p":"15,834.87","totalRevenue_p":"9,277.58","totalPromotionAmount_p":"57.36"},{"registerCount":8,"depositCount":57,"totalDeposit":"18049","totalWithdraw":"19682","totalWithdrawFee":"0","totalBetAmount":"231658.89","totalNetWin":"-3573.775","totalRevenue":"-1633.00","jackpot":"0.00","jpContribution":"0.00","totalPromotionAmount":"10.00","date_mmdd":"02-04","totalDeposit_p":"18,049.00","totalWithdraw_p":"19,682.00","totalBetAmount_p":"231,658.89","totalNetWin_p":"-3,573.78","totalRevenue_p":"-1,633.00","totalPromotionAmount_p":"10.00"},{"registerCount":8,"depositCount":51,"totalDeposit":"11623","totalWithdraw":"21958","totalWithdrawFee":"0","totalBetAmount":"98624.25","totalNetWin":"-3032.481","totalRevenue":"-10335.00","jackpot":"0.00","jpContribution":"0.00","totalPromotionAmount":"235.64","date_mmdd":"02-05","totalDeposit_p":"11,623.00","totalWithdraw_p":"21,958.00","totalBetAmount_p":"98,624.25","totalNetWin_p":"-3,032.48","totalRevenue_p":"-10,335.00","totalPromotionAmount_p":"235.64"},{"registerCount":9,"depositCount":41,"totalDeposit":"11496","totalWithdraw":"10197","totalWithdrawFee":"0","totalBetAmount":"115093.6929","totalNetWin":"882.7929","totalRevenue":"1299.00","jackpot":"0.00","jpContribution":"0.00","totalPromotionAmount":"10.00","date_mmdd":"02-06","totalDeposit_p":"11,496.00","totalWithdraw_p":"10,197.00","totalBetAmount_p":"115,093.69","totalNetWin_p":"882.79","totalRevenue_p":"1,299.00","totalPromotionAmount_p":"10.00"},{"registerCount":11,"depositCount":38,"totalDeposit":"11351","totalWithdraw":"7437","totalWithdrawFee":"0","totalBetAmount":"119859.75","totalNetWin":"3045.36","totalRevenue":"3914.00","jackpot":"0.00","jpContribution":"0.00","totalPromotionAmount":"19.68","date_mmdd":"02-07","totalDeposit_p":"11,351.00","totalWithdraw_p":"7,437.00","totalBetAmount_p":"119,859.75","totalNetWin_p":"3,045.36","totalRevenue_p":"3,914.00","totalPromotionAmount_p":"19.68"},{"registerCount":2,"depositCount":38,"totalDeposit":"15291","totalWithdraw":"11700","totalWithdrawFee":"0","totalBetAmount":"271539.5","totalNetWin":"2009.93","totalRevenue":"3591.00","jackpot":"0.00","jpContribution":"0.00","totalPromotionAmount":"29.02","date_mmdd":"02-08","totalDeposit_p":"15,291.00","totalWithdraw_p":"11,700.00","totalBetAmount_p":"271,539.50","totalNetWin_p":"2,009.93","totalRevenue_p":"3,591.00","totalPromotionAmount_p":"29.02"},{"registerCount":7,"depositCount":54,"totalDeposit":"23367","totalWithdraw":"13550","totalWithdrawFee":"0","totalBetAmount":"305008.45","totalNetWin":"12602.28","totalRevenue":"9817.00","jackpot":"0.00","jpContribution":"0.00","totalPromotionAmount":"10.00","date_mmdd":"02-09","totalDeposit_p":"23,367.00","totalWithdraw_p":"13,550.00","totalBetAmount_p":"305,008.45","totalNetWin_p":"12,602.28","totalRevenue_p":"9,817.00","totalPromotionAmount_p":"10.00"},{"registerCount":6,"depositCount":68,"totalDeposit":"45407","totalWithdraw":"15200","totalWithdrawFee":"0","totalBetAmount":"271802.27","totalNetWin":"29462.641","totalRevenue":"30207.00","jackpot":"0.00","jpContribution":"0.00","totalPromotionAmount":"30.91","date_mmdd":"02-10","totalDeposit_p":"45,407.00","totalWithdraw_p":"15,200.00","totalBetAmount_p":"271,802.27","totalNetWin_p":"29,462.64","totalRevenue_p":"30,207.00","totalPromotionAmount_p":"30.91"},{"registerCount":5,"depositCount":41,"totalDeposit":"10146","totalWithdraw":"12699","totalWithdrawFee":"0","totalBetAmount":"136911.7","totalNetWin":"-1252.836","totalRevenue":"-2553.00","jackpot":"0.00","jpContribution":"0.00","totalPromotionAmount":"391.04","date_mmdd":"02-11","totalDeposit_p":"10,146.00","totalWithdraw_p":"12,699.00","totalBetAmount_p":"136,911.70","totalNetWin_p":"-1,252.84","totalRevenue_p":"-2,553.00","totalPromotionAmount_p":"391.04"},{"registerCount":5,"depositCount":41,"totalDeposit":"13019","totalWithdraw":"1600","totalWithdrawFee":"0","totalBetAmount":"120677.9","totalNetWin":"10713.64","totalRevenue":"11419.00","jackpot":"0.00","jpContribution":"0.00","totalPromotionAmount":"23.30","date_mmdd":"02-12","totalDeposit_p":"13,019.00","totalWithdraw_p":"1,600.00","totalBetAmount_p":"120,677.90","totalNetWin_p":"10,713.64","totalRevenue_p":"11,419.00","totalPromotionAmount_p":"23.30"},{"registerCount":6,"depositCount":47,"totalDeposit":"9643","totalWithdraw":"4900","totalWithdrawFee":"0","totalBetAmount":"101843.35","totalNetWin":"4877.31","totalRevenue":"4743.00","jackpot":"0.00","jpContribution":"0.00","totalPromotionAmount":"16.51","date_mmdd":"02-13","totalDeposit_p":"9,643.00","totalWithdraw_p":"4,900.00","totalBetAmount_p":"101,843.35","totalNetWin_p":"4,877.31","totalRevenue_p":"4,743.00","totalPromotionAmount_p":"16.51"},{"registerCount":6,"depositCount":23,"totalDeposit":"5470.04","totalWithdraw":"4900","totalWithdrawFee":"0","totalBetAmount":"106585.7","totalNetWin":"1403.84","totalRevenue":"570.04","jackpot":"0.00","jpContribution":"0.00","totalPromotionAmount":"22.40","date_mmdd":"02-14","totalDeposit_p":"5,470.04","totalWithdraw_p":"4,900.00","totalBetAmount_p":"106,585.70","totalNetWin_p":"1,403.84","totalRevenue_p":"570.04","totalPromotionAmount_p":"22.40"},{"registerCount":6,"depositCount":41,"totalDeposit":"18358.01","totalWithdraw":"1635","totalWithdrawFee":"0","totalBetAmount":"128910.7","totalNetWin":"12393.05","totalRevenue":"16723.01","jackpot":"0.00","jpContribution":"0.00","totalPromotionAmount":"10.00","date_mmdd":"02-15","totalDeposit_p":"18,358.01","totalWithdraw_p":"1,635.00","totalBetAmount_p":"128,910.70","totalNetWin_p":"12,393.05","totalRevenue_p":"16,723.01","totalPromotionAmount_p":"10.00"},{"registerCount":6,"depositCount":31,"totalDeposit":"6539.63","totalWithdraw":"26500","totalWithdrawFee":"0","totalBetAmount":"214120","totalNetWin":"-15883.61","totalRevenue":"-19960.37","jackpot":"0.00","jpContribution":"0.00","totalPromotionAmount":"20.00","date_mmdd":"02-16","totalDeposit_p":"6,539.63","totalWithdraw_p":"26,500.00","totalBetAmount_p":"214,120.00","totalNetWin_p":"-15,883.61","totalRevenue_p":"-19,960.37","totalPromotionAmount_p":"20.00"},{"registerCount":3,"depositCount":42,"totalDeposit":"13202.06","totalWithdraw":"9640","totalWithdrawFee":"0","totalBetAmount":"85718.85","totalNetWin":"3727.24","totalRevenue":"3562.06","jackpot":"0.00","jpContribution":"0.00","totalPromotionAmount":"0.00","date_mmdd":"02-17","totalDeposit_p":"13,202.06","totalWithdraw_p":"9,640.00","totalBetAmount_p":"85,718.85","totalNetWin_p":"3,727.24","totalRevenue_p":"3,562.06","totalPromotionAmount_p":"0.00"},{"registerCount":6,"depositCount":31,"totalDeposit":"7783","totalWithdraw":"2657","totalWithdrawFee":"0","totalBetAmount":"83724","totalNetWin":"2557.348","totalRevenue":"5126.00","jackpot":"0.00","jpContribution":"0.00","totalPromotionAmount":"0.00","date_mmdd":"02-18","totalDeposit_p":"7,783.00","totalWithdraw_p":"2,657.00","totalBetAmount_p":"83,724.00","totalNetWin_p":"2,557.35","totalRevenue_p":"5,126.00","totalPromotionAmount_p":"0.00"},{"registerCount":9,"depositCount":40,"totalDeposit":"10356","totalWithdraw":"5215","totalWithdrawFee":"0","totalBetAmount":"118503.35","totalNetWin":"7874.77","totalRevenue":"5141.00","jackpot":"0.00","jpContribution":"0.00","totalPromotionAmount":"19.90","date_mmdd":"02-19","totalDeposit_p":"10,356.00","totalWithdraw_p":"5,215.00","totalBetAmount_p":"118,503.35","totalNetWin_p":"7,874.77","totalRevenue_p":"5,141.00","totalPromotionAmount_p":"19.90"},{"registerCount":1,"depositCount":28,"totalDeposit":"9439","totalWithdraw":"10522","totalWithdrawFee":"0","totalBetAmount":"89821.25","totalNetWin":"-1663.3","totalRevenue":"-1083.00","jackpot":"0.00","jpContribution":"0.00","totalPromotionAmount":"10.00","date_mmdd":"02-20","totalDeposit_p":"9,439.00","totalWithdraw_p":"10,522.00","totalBetAmount_p":"89,821.25","totalNetWin_p":"-1,663.30","totalRevenue_p":"-1,083.00","totalPromotionAmount_p":"10.00"}],"total":{"registerCount":"127","depositCount":"844","totalDeposit":"293,989.84","totalWithdraw":"206,517.00","totalBetAmount":"3,069,607.80","totalNetWin":"90,329.19","totalRevenue":"87,472.84","totalPromotionAmount":"1,234.23"}}