{"records":[{"gameKindId":"1","details":[{"brand":"JDB","gameKindCode":"1-","gameKindId":1,"netWin":"306.400000","ownNetWin":"0.000000","memberCount":"3","txnCount":"331","totalBets":"796.000000","jackpot":"0.000000","jpContribution":"0.000000"},{"brand":"JILI","gameKindCode":"1-","gameKindId":1,"netWin":"424.820000","ownNetWin":"0.000000","memberCount":"6","txnCount":"1388","totalBets":"3914.000000","jackpot":"0.000000","jpContribution":"0.000000"},{"brand":"JOKER","gameKindCode":"1-","gameKindId":1,"netWin":"26.500000","ownNetWin":"0.000000","memberCount":"3","txnCount":"593","totalBets":"2275.000000","jackpot":"0.000000","jpContribution":"0.000000"},{"brand":"MGP","gameKindCode":"1-","gameKindId":1,"netWin":"501.000000","ownNetWin":"0.000000","memberCount":"1","txnCount":"126","totalBets":"1260.000000","jackpot":"0.000000","jpContribution":"0.000000"},{"brand":"PGA","gameKindCode":"1-","gameKindId":1,"netWin":"4181.330000","ownNetWin":"0.000000","memberCount":"32","txnCount":"17369","totalBets":"60869.000000","jackpot":"0.000000","jpContribution":"0.000000"},{"brand":"PTO","gameKindCode":"1-","gameKindId":1,"netWin":"152.000000","ownNetWin":"0.000000","memberCount":"1","txnCount":"830","totalBets":"3516.000000","jackpot":"0.000000","jpContribution":"0.000000"},{"brand":"SG","gameKindCode":"1-","gameKindId":1,"netWin":"654.800000","ownNetWin":"0.000000","memberCount":"2","txnCount":"744","totalBets":"6166.000000","jackpot":"0.000000","jpContribution":"0.000000"}],"memberCount":"48","txnCount":"21381","totalBets":"78796","netWin":"6246.85","ownNetWin":"0","jackpot":"0","jpContribution":"0"},{"gameKindId":"6","details":[{"brand":"AW","gameKindCode":"5-6-","gameKindId":6,"netWin":"20.000000","ownNetWin":"0.000000","memberCount":"1","txnCount":"127","totalBets":"2576.400000","jackpot":"0.000000","jpContribution":"0.000000"},{"brand":"FC","gameKindCode":"5-6-","gameKindId":6,"netWin":"298.000000","ownNetWin":"0.000000","memberCount":"2","txnCount":"55","totalBets":"7272.000000","jackpot":"0.000000","jpContribution":"0.000000"},{"brand":"JDB","gameKindCode":"5-6-","gameKindId":6,"netWin":"985.100000","ownNetWin":"0.000000","memberCount":"6","txnCount":"95","totalBets":"18599.200000","jackpot":"0.000000","jpContribution":"0.000000"},{"brand":"JILI","gameKindCode":"5-6-","gameKindId":6,"netWin":"4205.500000","ownNetWin":"0.000000","memberCount":"20","txnCount":"6625","totalBets":"75988.000000","jackpot":"0.000000","jpContribution":"0.000000"},{"brand":"SG","gameKindCode":"5-6-","gameKindId":6,"netWin":"-285.800000","ownNetWin":"0.000000","memberCount":"2","txnCount":"4","totalBets":"9361.300000","jackpot":"0.000000","jpContribution":"0.000000"}],"memberCount":"31","txnCount":"6906","totalBets":"113796.9","netWin":"5222.8","ownNetWin":"0","jackpot":"0","jpContribution":"0"},{"gameKindId":"8","details":[{"brand":"SABAV2","gameKindCode":"8-","gameKindId":8,"netWin":"-2434.390000","ownNetWin":"0.000000","memberCount":"3","txnCount":"167","totalBets":"247607.000000","jackpot":"0.000000","jpContribution":"0.000000"},{"brand":"SBOV2","gameKindCode":"8-","gameKindId":8,"netWin":"-15945.950000","ownNetWin":"0.000000","memberCount":"2","txnCount":"20","totalBets":"48414.100000","jackpot":"0.000000","jpContribution":"0.000000"}],"memberCount":"5","txnCount":"187","totalBets":"296021.1","netWin":"-18380.34","ownNetWin":"0","jackpot":"0","jpContribution":"0"},{"gameKindId":"13","details":[{"brand":"SEXY","gameKindCode":"4-13-","gameKindId":13,"netWin":"470.000000","ownNetWin":"0.000000","memberCount":"1","txnCount":"24","totalBets":"810.000000","jackpot":"0.000000","jpContribution":"0.000000"}],"memberCount":"1","txnCount":"24","totalBets":"810","netWin":"470","ownNetWin":"0","jackpot":"0","jpContribution":"0"},{"gameKindId":"21","details":[{"brand":"AW","gameKindCode":"5-21-","gameKindId":21,"netWin":"60.000000","ownNetWin":"0.000000","memberCount":"1","txnCount":"8","totalBets":"250.000000","jackpot":"0.000000","jpContribution":"0.000000"}],"memberCount":"1","txnCount":"8","totalBets":"250","netWin":"60","ownNetWin":"0","jackpot":"0","jpContribution":"0"}],"sum":{"memberCount":"86","txnCount":"28506","totalBets":"489674","netWin":"-6380.69","ownNetWin":"0","jackpot":"0","jpContribution":"0"}}